adalflow/__init__.py
adalflow/apps/__init__.py
adalflow/apps/cli_permission_handler.py
adalflow/apps/fastapi_permission_handler.py
adalflow/apps/permission_manager.py
adalflow/components/__init__.py
adalflow/components/agent/README.md
adalflow/components/agent/__init__.py
adalflow/components/agent/agent.py
adalflow/components/agent/prompts.py
adalflow/components/agent/react.py
adalflow/components/agent/runner.py
adalflow/components/data_process/__init__.py
adalflow/components/data_process/data_components.py
adalflow/components/data_process/text_splitter.py
adalflow/components/memory/__init__.py
adalflow/components/memory/memory.py
adalflow/components/model_client/__init__.py
adalflow/components/model_client/anthropic_client.py
adalflow/components/model_client/azureai_client.py
adalflow/components/model_client/bedrock_client.py
adalflow/components/model_client/chat_completion_to_response_converter.py
adalflow/components/model_client/cohere_client.py
adalflow/components/model_client/deepseek_client.py
adalflow/components/model_client/fireworks_client.py
adalflow/components/model_client/google_client.py
adalflow/components/model_client/groq_client.py
adalflow/components/model_client/mistral_client.py
adalflow/components/model_client/ollama_client.py
adalflow/components/model_client/openai_client.py
adalflow/components/model_client/sambanova_client.py
adalflow/components/model_client/together_client.py
adalflow/components/model_client/transformers_client.py
adalflow/components/model_client/utils.py
adalflow/components/model_client/xai_client.py
adalflow/components/output_parsers/__init__.py
adalflow/components/output_parsers/dataclass_parser.py
adalflow/components/output_parsers/outputs.py
adalflow/components/retriever/__init__.py
adalflow/components/retriever/bm25_retriever.py
adalflow/components/retriever/faiss_retriever.py
adalflow/components/retriever/lancedb_retriver.py
adalflow/components/retriever/llm_retriever.py
adalflow-1.1.3.dist-info/METADATA
adalflow-1.1.3.dist-info/WHEEL
adalflow-1.1.3.dist-info/licenses/LICENSE.md
adalflow-1.1.3.dist-info/RECORD
