Metadata-Version: 2.4
Name: adalflow
Version: 1.1.3
Summary: The Library to Build and Auto-optimize LLM Applications
License: MIT
License-File: LICENSE.md
Keywords: LLM,NLP,RAG,devtools,retrieval,agent
Author: Li Yin
Author-email: li@sylphai.com
Maintainer: Li Yin
Maintainer-email: li@sylphai.com
Requires-Python: >=3.9,<4.0
Classifier: License :: OSI Approved :: MIT License
Classifier: Programming Language :: Python :: 3
Classifier: Programming Language :: Python :: 3.9
Classifier: Programming Language :: Python :: 3.10
Classifier: Programming Language :: Python :: 3.11
Classifier: Programming Language :: Python :: 3.12
Classifier: Programming Language :: Python :: 3.13
Classifier: Programming Language :: Python :: 3.14
Classifier: Topic :: Scientific/Engineering :: Artificial Intelligence
Classifier: Topic :: Software Development :: Build Tools
Classifier: Topic :: Software Development :: Libraries :: Application Frameworks
Classifier: Topic :: Software Development :: Libraries :: Python Modules
Provides-Extra: anthropic
Provides-Extra: azure
Provides-Extra: bedrock
Provides-Extra: cohere
Provides-Extra: datasets
Provides-Extra: faiss-cpu
Provides-Extra: fireworks-ai
Provides-Extra: google-generativeai
Provides-Extra: groq
Provides-Extra: lancedb
Provides-Extra: mcp
Provides-Extra: mistralai
Provides-Extra: ollama
Provides-Extra: openai
Provides-Extra: pgvector
Provides-Extra: sqlalchemy
Provides-Extra: together
Provides-Extra: torch
Requires-Dist: PyYAML (>=6.0.1)
Requires-Dist: anthropic (>=0.55.0) ; extra == "anthropic"
Requires-Dist: asyncstdlib (>=3.13.1,<4.0.0)
Requires-Dist: azure-core (>=1.24.0) ; extra == "azure"
Requires-Dist: azure-identity (>=1.12.0) ; extra == "azure"
Requires-Dist: backoff (>=2.2.1,<3.0.0)
Requires-Dist: boto3 (>=1.35.19,<2.0.0) ; extra == "bedrock"
Requires-Dist: cohere (>=5.5.8) ; extra == "cohere"
Requires-Dist: colorama (>=0.4.6,<0.5.0)
Requires-Dist: diskcache (>=5.6.3,<6.0.0)
Requires-Dist: faiss-cpu (>=1.8.0) ; extra == "faiss-cpu"
Requires-Dist: google-generativeai (>=0.7.2) ; extra == "google-generativeai"
Requires-Dist: groq (>=0.9.0) ; extra == "groq"
Requires-Dist: jinja2 (>=3.1.3,<4.0.0)
Requires-Dist: jsonlines (>=4.0.0,<5.0.0)
Requires-Dist: lancedb (>=0.5.2) ; extra == "lancedb"
Requires-Dist: mcp (>=1.9.4,<2.0.0) ; (python_version >= "3.10") and (extra == "mcp")
Requires-Dist: nest-asyncio (>=1.6.0,<2.0.0)
Requires-Dist: numpy (<2.1.0) ; python_version < "3.10"
Requires-Dist: numpy ; python_version >= "3.10"
Requires-Dist: ollama (>=0.2.1) ; extra == "ollama"
Requires-Dist: openai (>=1.97.1) ; extra == "openai"
Requires-Dist: pgvector (>=0.3.1) ; extra == "pgvector"
Requires-Dist: pydantic (>=2.0.0)
Requires-Dist: pytest-asyncio (>=1.0.0,<2.0.0)
Requires-Dist: python-dotenv (>=1.0.1,<2.0.0)
Requires-Dist: sqlalchemy (>=2.0.30) ; extra == "sqlalchemy"
Requires-Dist: tiktoken (>=0.3.3)
Requires-Dist: together (>=1.3.14) ; extra == "together"
Requires-Dist: torch (>=2.3.1) ; extra == "torch"
Requires-Dist: tqdm (>=4.66.4,<5.0.0)
Project-URL: Repository, https://github.com/SylphAI-Inc/AdalFlow
